{
  "data": {
    "id": "289",
    "type": "documents",
    "attributes": {
      "policy": {
        "access": "no_access",
        "permissions": [
          {
            "resource": {
              "id": "4656",
              "type": "projects"
            },
            "access": "edit"
          }
        ]
      },
      "discussion_links": [

      ],
      "extended_attributes": {
        "extended_metadata_type_id": "447",
        "attribute_map": {
          "role_email": "alice@email.com",
          "role_phone": "0012345",
          "role_name": {
            "first_name": "alice",
            "last_name": "liddell"
          },
          "role_address": {
            "street": "wonder",
            "city": "land"
          }
        }
      },
      "title": "A Maximally Patched Document",
      "license": "CC-BY-4.0",
      "description": "A report about the thing that happened",
      "latest_version": 1,
      "tags": [
        "tag1",
        "tag2",
        "tag3"
      ],
      "versions": [
        {
          "version": 1,
          "revision_comments": null,
          "url": "http://localhost:3000/documents/289?version=1",
          "doi": null
        }
      ],
      "version": 1,
      "revision_comments": null,
      "created_at": "2024-07-03T13:54:14.000Z",
      "updated_at": "2024-07-03T13:54:14.000Z",
      "doi": null,
      "content_blobs": [
        {
          "original_filename": "file-304",
          "url": null,
          "md5sum": "713ff0a7ead2a1f98a0ee54f67ebcd9f",
          "sha1sum": "3f459d9381889e68408f7e4cdf3f07620504daf2",
          "content_type": "application/pdf",
          "link": "http://localhost:3000/documents/289/content_blobs/1448",
          "size": 10
        }
      ],
      "creators": [
        {
          "profile": "/people/4394",
          "family_name": "Last",
          "given_name": "Person3653",
          "affiliation": "An Institution: 4466",
          "orcid": null
        }
      ],
      "other_creators": "John Smith, Jane Smith"
    },
    "relationships": {
      "creators": {
        "data": [
          {
            "id": "4394",
            "type": "people"
          }
        ]
      },
      "submitter": {
        "data": [
          {
            "id": "4393",
            "type": "people"
          }
        ]
      },
      "people": {
        "data": [
          {
            "id": "4393",
            "type": "people"
          },
          {
            "id": "4394",
            "type": "people"
          }
        ]
      },
      "projects": {
        "data": [
          {
            "id": "4656",
            "type": "projects"
          }
        ]
      },
      "investigations": {
        "data": [
          {
            "id": "849",
            "type": "investigations"
          }
        ]
      },
      "studies": {
        "data": [
          {
            "id": "747",
            "type": "studies"
          }
        ]
      },
      "assays": {
        "data": [
          {
            "id": "614",
            "type": "assays"
          }
        ]
      },
      "publications": {
        "data": [

        ]
      },
      "workflows": {
        "data": [
          {
            "id": "206",
            "type": "workflows"
          }
        ]
      }
    },
    "links": {
      "self": "/documents/289?version=1"
    },
    "meta": {
      "created": "2024-07-03T13:54:14.000Z",
      "modified": "2024-07-03T13:54:14.000Z",
      "api_version": "0.3",
      "base_url": "http://localhost:3000",
      "uuid": "a7f079d0-1b71-013d-1ffe-0a81884ed284"
    }
  },
  "jsonapi": {
    "version": "1.0"
  }
}