{
    "data": [
        {
            "id": "364",
            "type": "people",
            "attributes": {
                "title": "Hadas Leonov"
            },
            "links": {
                "self": "/people/364"
            }
        },
        {
            "id": "321",
            "type": "people",
            "attributes": {
                "title": "Finn Bacall"
            },
            "links": {
                "self": "/people/321"
            }
        },
        {
            "id": "134",
            "type": "people",
            "attributes": {
                "title": "Stuart Owen"
            },
            "links": {
                "self": "/people/134"
            }
        }
    ],
    "jsonapi": {
        "version": "1.0"
    },
    "meta": {
        "base_url": "https://testing.sysmo-db.org",
        "api_version": "0.1"
    }
}