{
  "data": {
    "id": "1039988361",
    "type": "people",
    "attributes": {
      "avatar": "/people/1039988361/avatars/37",
      "title": "Maximilian Maxi-Mum",
      "description": "A person with all possible details",
      "first_name": "Maximilian",
      "last_name": "Maxi-Mum",
      "orcid": "https://orcid.org/0000-0001-9842-9718",
      "mbox_sha1sum": "a19916c29e3857b918504789a62950d3542f94ec",
      "expertise": [
        "fishing",
        "golf"
      ],
      "tools": [
        "fishing rod"
      ],
      "login": "max_person_user"
    },
    "relationships": {
      "projects": {
        "data": [
          {
            "id": "1022252437",
            "type": "projects"
          }
        ]
      },
      "institutions": {
        "data": [
          {
            "id": "980192883",
            "type": "institutions"
          }
        ]
      },
      "investigations": {
        "data": [
          {
            "id": "973655106",
            "type": "investigations"
          }
        ]
      },
      "studies": {
        "data": [
          {
            "id": "1060385137",
            "type": "studies"
          }
        ]
      },
      "assays": {
        "data": [
          {
            "id": "1035386882",
            "type": "assays"
          }
        ]
      },
      "data_files": {
        "data": [
          {
            "id": "883654361",
            "type": "data_files"
          }
        ]
      },
      "models": {
        "data": [
          {
            "id": "1004285589",
            "type": "models"
          }
        ]
      },
      "sops": {
        "data": [
          {
            "id": "1055250491",
            "type": "sops"
          }
        ]
      },
      "publications": {
        "data": [
          {
            "id": "303",
            "type": "publications"
          }
        ]
      },
      "presentations": {
        "data": [
          {
            "id": "118",
            "type": "presentations"
          }
        ]
      },
      "events": {
        "data": [
          {
            "id": "1025618752",
            "type": "events"
          }
        ]
      },
      "documents": {
        "data": [
          {
            "id": "267",
            "type": "documents"
          }
        ]
      },
      "workflows": {
        "data": [
          {
            "id": "183",
            "type": "workflows"
          }
        ]
      },
      "collections": {
        "data": [
          {
            "id": "103",
            "type": "collections"
          }
        ]
      }
    },
    "links": {
      "self": "/people/1039988361"
    },
    "meta": {
      "created": "2024-06-20T12:38:46.000Z",
      "modified": "2024-06-20T12:38:46.000Z",
      "api_version": "0.3",
      "base_url": "http://localhost:3000",
      "uuid": "f5c5aed0-112f-013d-1f9d-0a81884ed284"
    }
  },
  "jsonapi": {
    "version": "1.0"
  }
}