{
  "data": {
    "id": "2216",
    "type": "programmes",
    "attributes": {
      "discussion_links": [
        {
          "id": "1481",
          "label": "Slack",
          "url": "http://www.slack.com/"
        }
      ],
      "avatar": null,
      "title": "A Maximal Programme",
      "description": "A very exciting programme",
      "web_page": "http://www.synbiochem.co.uk",
      "funding_details": "Someone is funding this for me",
      "funding_codes": [
        "DFG"
      ]
    },
    "relationships": {
      "administrators": {
        "data": [
          {
            "id": "1040009390",
            "type": "people"
          }
        ]
      },
      "people": {
        "data": [

        ]
      },
      "projects": {
        "data": [
          {
            "id": "1022271899",
            "type": "projects"
          }
        ]
      },
      "institutions": {
        "data": [
          {
            "id": "980209048",
            "type": "institutions"
          }
        ]
      },
      "investigations": {
        "data": [
          {
            "id": "973657527",
            "type": "investigations"
          }
        ]
      },
      "studies": {
        "data": [
          {
            "id": "1060387241",
            "type": "studies"
          }
        ]
      },
      "assays": {
        "data": [
          {
            "id": "1035388642",
            "type": "assays"
          }
        ]
      },
      "data_files": {
        "data": [
          {
            "id": "883655091",
            "type": "data_files"
          }
        ]
      },
      "models": {
        "data": [
          {
            "id": "1004287423",
            "type": "models"
          }
        ]
      },
      "sops": {
        "data": [
          {
            "id": "1055251195",
            "type": "sops"
          }
        ]
      },
      "publications": {
        "data": [
          {
            "id": "1433",
            "type": "publications"
          }
        ]
      },
      "presentations": {
        "data": [
          {
            "id": "593",
            "type": "presentations"
          }
        ]
      },
      "events": {
        "data": [
          {
            "id": "1025619150",
            "type": "events"
          }
        ]
      },
      "documents": {
        "data": [
          {
            "id": "1514",
            "type": "documents"
          }
        ]
      },
      "workflows": {
        "data": [
          {
            "id": "1024",
            "type": "workflows"
          }
        ]
      },
      "collections": {
        "data": [

        ]
      }
    },
    "links": {
      "self": "/programmes/2216"
    },
    "meta": {
      "created": "2023-03-14T12:45:08.000Z",
      "modified": "2023-03-14T12:45:08.000Z",
      "api_version": "0.3",
      "base_url": "http://localhost:3000",
      "uuid": "fa128a70-a493-013b-b230-2c91a17e7bb9"
    }
  },
  "jsonapi": {
    "version": "1.0"
  }
}