{
  "data": {
    "id": "79",
    "type": "projects",
    "attributes": {
      "discussion_links": [
        {
          "id": "8",
          "label": "Slack",
          "url": "http://www.slack.com/"
        }
      ],
      "avatar": "/projects/79/avatars/2",
      "title": "A Maximal Project",
      "description": "A Taverna project",
      "web_page": "http://www.taverna.org.uk",
      "wiki_page": "http://www.mygrid.org.uk",
      "default_license": "Other (Open)",
      "start_date": "2010-01-01",
      "end_date": "2014-06-21",
      "default_policy": {
        "access": "no_access",
        "permissions": [

        ]
      },
      "members": [
        {
          "person_id": "65",
          "institution_id": "68"
        }
      ],
      "use_default_policy": true
    },
    "relationships": {
      "project_administrators": {
        "data": [

        ]
      },
      "pals": {
        "data": [

        ]
      },
      "asset_housekeepers": {
        "data": [

        ]
      },
      "asset_gatekeepers": {
        "data": [

        ]
      },
      "organisms": {
        "data": [

        ]
      },
      "human_diseases": {
        "data": [

        ]
      },
      "people": {
        "data": [
          {
            "id": "65",
            "type": "people"
          }
        ]
      },
      "institutions": {
        "data": [
          {
            "id": "68",
            "type": "institutions"
          }
        ]
      },
      "programmes": {
        "data": [
          {
            "id": "5",
            "type": "programmes"
          }
        ]
      },
      "investigations": {
        "data": [
          {
            "id": "14",
            "type": "investigations"
          }
        ]
      },
      "studies": {
        "data": [
          {
            "id": "12",
            "type": "studies"
          }
        ]
      },
      "assays": {
        "data": [
          {
            "id": "10",
            "type": "assays"
          }
        ]
      },
      "data_files": {
        "data": [
          {
            "id": "4",
            "type": "data_files"
          }
        ]
      },
      "file_templates": {
        "data": [

        ]
      },
      "placeholders": {
        "data": [

        ]
      },
      "models": {
        "data": [
          {
            "id": "14",
            "type": "models"
          }
        ]
      },
      "sops": {
        "data": [
          {
            "id": "4",
            "type": "sops"
          }
        ]
      },
      "publications": {
        "data": [
          {
            "id": "4",
            "type": "publications"
          }
        ]
      },
      "presentations": {
        "data": [
          {
            "id": "2",
            "type": "presentations"
          }
        ]
      },
      "events": {
        "data": [
          {
            "id": "2",
            "type": "events"
          }
        ]
      },
      "documents": {
        "data": [
          {
            "id": "4",
            "type": "documents"
          }
        ]
      },
      "workflows": {
        "data": [
          {
            "id": "2",
            "type": "workflows"
          }
        ]
      }
    },
    "links": {
      "self": "/projects/79"
    },
    "meta": {
      "created": "2022-05-12T14:13:36.000Z",
      "modified": "2022-05-12T14:13:36.000Z",
      "api_version": "0.3",
      "base_url": "http://localhost:3000",
      "uuid": "a37a2df0-b42b-013a-0f20-0a81884ed284"
    }
  },
  "jsonapi": {
    "version": "1.0"
  }
}