{
  "data": {
    "id": "292",
    "type": "samples",
    "attributes": {
      "discussion_links": [],
      "title": "Fred Bloggs",
      "tags": [],
      "created_at": "2021-08-31T13:38:39.000Z",
      "updated_at": "2021-08-31T13:38:39.000Z",
      "other_creators": null,
      "attribute_map": {
        "full_name": "Fred Bloggs",
        "address": "3 School Road",
        "postcode": "M13 9PL"
      }
    },
    "relationships": {
      "creators": {
        "data": [

        ]
      },
      "submitter": {
        "data": [
          {
            "id": "1056",
            "type": "people"
          }
        ]
      },
      "sample_type": {
        "data": {
          "id": "354",
          "type": "sample_types"
        }
      },
      "projects": {
        "data": [
          {
            "id": "1042",
            "type": "projects"
          }
        ]
      },
      "data_files": {
        "data": [

        ]
      },
      "people": {
        "data": [
          {
            "id": "1056",
            "type": "people"
          }
        ]
      }
    },
    "links": {
      "self": "/samples/292"
    },
    "meta": {
      "created": "2021-08-31T13:38:39.000Z",
      "modified": "2021-08-31T13:38:39.000Z",
      "api_version": "0.3",
      "uuid": "ac934970-ec8e-0139-2586-000c29095f88",
      "base_url": "http://localhost:3000"
    }
  },
  "jsonapi": {
    "version": "1.0"
  }
}